setup.py
gozerplugs/8b.py
gozerplugs/__init__.py
gozerplugs/alarm.py
gozerplugs/anon.py
gozerplugs/autoreply.py
gozerplugs/autovoice.py
gozerplugs/away.py
gozerplugs/banner.py
gozerplugs/bash.py
gozerplugs/beats.py
gozerplugs/bender.py
gozerplugs/birthday.py
gozerplugs/botsnack.py
gozerplugs/bugtracker.py
gozerplugs/buzz.py
gozerplugs/chatlog.py
gozerplugs/cloud.py
gozerplugs/country.py
gozerplugs/dns.py
gozerplugs/dope.py
gozerplugs/drinks.py
gozerplugs/echo.py
gozerplugs/event.py
gozerplugs/facts.py
gozerplugs/fans.py
gozerplugs/gcalc.py
gozerplugs/gcollect.py
gozerplugs/grab.py
gozerplugs/greeting.py
gozerplugs/hello.py
gozerplugs/hex2ip.py
gozerplugs/hexjoin.py
gozerplugs/httpwatch.py
gozerplugs/identify.py
gozerplugs/idle.py
gozerplugs/infoitem.py
gozerplugs/ipcalc.py
gozerplugs/karma.py
gozerplugs/kickban.py
gozerplugs/lag.py
gozerplugs/lart.py
gozerplugs/lists.py
gozerplugs/lns.py
gozerplugs/log.py
gozerplugs/mac.py
gozerplugs/mail.py
gozerplugs/mailexceptions.py
gozerplugs/markov.py
gozerplugs/mash.py
gozerplugs/mpd.py
gozerplugs/oneliner.py
gozerplugs/ops.py
gozerplugs/pit.py
gozerplugs/powernick.py
gozerplugs/probe.py
gozerplugs/projecttracker.py
gozerplugs/quote.py
gozerplugs/rblcheck.py
gozerplugs/register.py
gozerplugs/relay.py
gozerplugs/remind.py
gozerplugs/rss.py
gozerplugs/search.py
gozerplugs/sed.py
gozerplugs/seen.py
gozerplugs/shakespear.py
gozerplugs/shop.py
gozerplugs/shoutcast.py
gozerplugs/snarf.py
gozerplugs/tcp.py
gozerplugs/tel.py
gozerplugs/throttle.py
gozerplugs/timebomb.py
gozerplugs/timer.py
gozerplugs/tinyurl.py
gozerplugs/todo.py
gozerplugs/topic.py
gozerplugs/trac.py
gozerplugs/translate.py
gozerplugs/twitter.py
gozerplugs/udp.py
gozerplugs/umode.py
gozerplugs/urban.py
gozerplugs/url.py
gozerplugs/weather.py
gozerplugs/whois.py
gozerplugs/wikipedia.py
gozerplugs/wikiquote.py
gozerplugs/wisdom.py
gozerplugs/wowwiki.py
gozerplugs/yahoo.py
gozerplugs.egg-info/PKG-INFO
gozerplugs.egg-info/SOURCES.txt
gozerplugs.egg-info/dependency_links.txt
gozerplugs.egg-info/top_level.txt
gozerplugs/tracserver/__init__.py
gozerplugs/tracserver/tserver.py
