Metadata-Version: 1.0
Name: gozerplugs
Version: 0.9.1.1
Summary: plugin package for gozerbot 
Home-page: http://gozerbot.org
Author: Bart Thate
Author-email: bthate@gmail.com
License: BSD
Platform: UNKNOWN
